hanpud/__init__.py
HanPud-0.1.dev0.dist-info/LICENSE
HanPud-0.1.dev0.dist-info/METADATA
HanPud-0.1.dev0.dist-info/WHEEL
HanPud-0.1.dev0.dist-info/top_level.txt
HanPud-0.1.dev0.dist-info/RECORD
